fontquery/__init__.py
fontquery/build.py
fontquery/cache.py
fontquery/client.py
fontquery/container.py
fontquery/diff.py
fontquery/frontend.py
fontquery/htmlformatter.py
fontquery/package.py
fontquery/pkgdiff.py
fontquery/version.py
fontquery/version.txt
fontquery/data/Containerfile
fontquery/scripts/fontquery-setup.sh
fontquery-1.32.dist-info/licenses/LICENSE
fontquery-1.32.dist-info/METADATA
fontquery-1.32.dist-info/WHEEL
fontquery-1.32.dist-info/entry_points.txt
fontquery-1.32.dist-info/top_level.txt
fontquery-1.32.dist-info/RECORD
