Metadata-Version: 2.4
Name: fontquery
Version: 1.32
Summary: Query a font in Fedora release
Author-email: Akira TAGOH <akira@tagoh.org>
License-Expression: MIT
Project-URL: Homepage, https://github.com/fedora-i18n/fontquery
Project-URL: Bug Tracker, https://github.com/fedora-i18n/fontquery/issues
Keywords: fedora,fonts
Classifier: Development Status :: 4 - Beta
Classifier: Environment :: Console
Classifier: Operating System :: POSIX :: Linux
Classifier: Programming Language :: Python :: 3
Requires-Python: >=3.11
License-File: LICENSE
Requires-Dist: markdown
Requires-Dist: langtable
Requires-Dist: pyxdg
Requires-Dist: termcolor
Requires-Dist: pyyaml
Dynamic: license-file
